{
  "version": "7",
  "dialect": "postgresql",
  "entries": [
    {
      "idx": 0,
      "version": "7",
      "when": 1736715022835,
      "tag": "0000_yellow_taskmaster",
      "breakpoints": true
    },
    {
      "idx": 1,
      "version": "7",
      "when": 1736719165656,
      "tag": "0001_slimy_goblin_queen",
      "breakpoints": true
    },
    {
      "idx": 2,
      "version": "7",
      "when": 1736785061822,
      "tag": "0002_lyrical_ultron",
      "breakpoints": true
    },
    {
      "idx": 3,
      "version": "7",
      "when": 1736803119756,
      "tag": "0003_third_ultron",
      "breakpoints": true
    },
    {
      "idx": 4,
      "version": "7",
      "when": 1737829817069,
      "tag": "0004_public_loa",
      "breakpoints": true
    },
    {
      "idx": 5,
      "version": "7",
      "when": 1737836565452,
      "tag": "0005_ambitious_ezekiel",
      "breakpoints": true
    },
    {
      "idx": 6,
      "version": "7",
      "when": 1738173733371,
      "tag": "0006_old_dragon_lord",
      "breakpoints": true
    },
    {
      "idx": 7,
      "version": "7",
      "when": 1738271649585,
      "tag": "0007_icy_micromacro",
      "breakpoints": true
    },
    {
      "idx": 8,
      "version": "7",
      "when": 1738289741550,
      "tag": "0008_tired_zarek",
      "breakpoints": true
    },
    {
      "idx": 9,
      "version": "7",
      "when": 1738335793668,
      "tag": "0009_pg_crypto",
      "breakpoints": true
    },
    {
      "idx": 10,
      "version": "7",
      "when": 1738336704349,
      "tag": "0010_sticky_silverclaw",
      "breakpoints": true
    },
    {
      "idx": 11,
      "version": "7",
      "when": 1738345559939,
      "tag": "0011_clammy_dark_beast",
      "breakpoints": true
    },
    {
      "idx": 12,
      "version": "7",
      "when": 1738346463163,
      "tag": "0012_harsh_lila_cheney",
      "breakpoints": true
    }
  ]
}